phimaker-0.3.0.dist-info/METADATA
phimaker-0.3.0.dist-info/WHEEL
phimaker/__init__.py
phimaker/_washboard_interface.py
phimaker/phimaker.cpython-313-arm-linux-gnueabihf.so
phimaker-0.3.0.dist-info/RECORD
